README.rst
setup.cfg
setup.py
pytest_scenario/__init__.py
pytest_scenario/exceptions.py
pytest_scenario/plugin.py
pytest_scenario.egg-info/PKG-INFO
pytest_scenario.egg-info/SOURCES.txt
pytest_scenario.egg-info/dependency_links.txt
pytest_scenario.egg-info/entry_points.txt
pytest_scenario.egg-info/requires.txt
pytest_scenario.egg-info/top_level.txt