Metadata-Version: 1.1
Name: pytest-scenario
Version: 1.0a2
Summary: pytest plugin for test scenarios
Home-page: https://github.com/OriMenashe/pytest-scenario
Author: Ori Menashe
Author-email: orim@live.com
License: WTFPL
Download-URL: https://github.com/OriMenashe/pytest-scenario/tarball/1.0a2
Keywords: testing,py.test,pytest,scenario
Platform: UNKNOWN
Classifier: Development Status :: 3 - Alpha
Classifier: Intended Audience :: Developers
Classifier: Operating System :: POSIX
Classifier: Operating System :: Microsoft :: Windows
Classifier: Operating System :: MacOS :: MacOS X
Classifier: Topic :: Software Development :: Quality Assurance
Classifier: Topic :: Software Development :: Testing
Classifier: Topic :: Utilities
Classifier: Programming Language :: Python
Classifier: Programming Language :: Python :: 3.4
